Metadata-Version: 1.0
Name: nome-pacote
Version: 1.0
Summary: Sua descrição entra aqui
Home-page: UNKNOWN
Author: Jhonatan
Author-email: jhonatan@hotmal.com
License: UNKNOWN
Keywords: camera
Platform: UNKNOWN
